slamcore_utils/__init__.py
slamcore_utils/arg_parser.py
slamcore_utils/data_converter.py
slamcore_utils/dataset_dir_converter.py
slamcore_utils/dataset_subdir_writer.py
slamcore_utils/fs.py
slamcore_utils/logging.py
slamcore_utils/math.py
slamcore_utils/measurement_type.py
slamcore_utils/openloris_converter.py
slamcore_utils/progress_bar.py
slamcore_utils/ros2/__init__.py
slamcore_utils/ros2/ros2_converter_plugin.py
slamcore_utils/ros2/ros2_converter_plugins/gnss.py
slamcore_utils/ros2/ros2_utils.py
slamcore_utils/ros_utils.py
slamcore_utils/scripts/convert_openloris.py
slamcore_utils/scripts/convert_rosbag2.py
slamcore_utils/scripts/setup_dataset.py
slamcore_utils/share/capture_infos/euroc_capture_info.json
slamcore_utils/share/capture_infos/openlorismain_capture_info.json
slamcore_utils/share/capture_infos/openlorismarket_capture_info.json
slamcore_utils/share/capture_infos/tum1024_capture_info.json
slamcore_utils/share/capture_infos/tum512_capture_info.json
slamcore_utils/share/setup_dataset.json
slamcore_utils/string.py
slamcore_utils/test_utils.py
slamcore_utils/utils.py
slamcore_utils-0.1.7.dist-info/LICENSE.md
slamcore_utils-0.1.7.dist-info/METADATA
slamcore_utils-0.1.7.dist-info/WHEEL
slamcore_utils-0.1.7.dist-info/entry_points.txt
slamcore_utils-0.1.7.dist-info/RECORD
