Metadata-Version: 2.1
Name: slamcore_utils
Version: 0.1.7
Summary: SLAMcore SLAM Utilities
Home-page: https://github.com/slamcore/slamcore_utils
License: BSD License
Author: Nikos Koukis
Author-email: nikolaos@slamcore.com
Requires-Python: >=3.6.8,<3.12
Classifier: License :: OSI Approved :: BSD License
Classifier: License :: Other/Proprietary License
Classifier: Operating System :: Unix
Classifier: Programming Language :: Python :: 3
Classifier: Programming Language :: Python :: 3.7
Classifier: Programming Language :: Python :: 3.8
Classifier: Programming Language :: Python :: 3.9
Classifier: Programming Language :: Python :: 3.10
Classifier: Programming Language :: Python :: 3.11
Classifier: Programming Language :: Python :: 3.6
Provides-Extra: ros2
Provides-Extra: tqdm
Requires-Dist: lark (>=1.1.5,<2.0.0) ; extra == "ros2"
Requires-Dist: numpy (>=1.19.5,<2.0.0) ; python_version < "3.9"
Requires-Dist: numpy ; python_version >= "3.9"
Requires-Dist: pillow (>=7.2.0,<8.0.0) ; extra == "ros2"
Requires-Dist: prompt-toolkit (>3.0,<=3.0.23)
Requires-Dist: pyyaml (>=6.0,<7.0) ; extra == "ros2"
Requires-Dist: questionary (>=1.10.0,<2.0.0)
Requires-Dist: tqdm (>=4.64.0,<5.0.0) ; extra == "tqdm"
Project-URL: Repository, https://github.com/slamcore/slamcore_utils
